seto/__init__.py
seto/__main__.py
seto/commands/config.py
seto/commands/deploy.py
seto/commands/down.py
seto/commands/mount.py
seto/commands/setup.py
seto/commands/umount.py
seto/commands/volumes.py
seto/core/command.py
seto/core/dns.py
seto/core/docker.py
seto/core/driver.py
seto/core/network.py
seto/core/package.py
seto/core/parser.py
seto/core/permissions.py
seto/core/shell.py
seto/core/swarm.py
seto/core/traefik.py
seto/core/volume.py
seto/drivers/nfs.py
seto/shells/local.py
seto/shells/remote.py
seto-3.8.0.dist-info/WHEEL
seto-3.8.0.dist-info/entry_points.txt
seto-3.8.0.dist-info/METADATA
seto-3.8.0.dist-info/RECORD
