Metadata-Version: 2.3
Name: seto
Version: 3.8.0
Summary: A Docker Swarm Deployment Manager
Keywords: docker,swarm,manager
Author: Sébastien Demanou
Author-email: Sébastien Demanou <demsking@gmail.com>
License: Apache-2.0
Classifier: Development Status :: 4 - Beta
Classifier: Intended Audience :: Developers
Classifier: Programming Language :: Python :: 3.11
Classifier: Operating System :: POSIX :: Linux
Requires-Dist: docker>=7.1.0
Requires-Dist: paramiko>=4.0.0
Requires-Dist: pyyaml>=6.0.3
Maintainer: Sébastien Demanou
Maintainer-email: Sébastien Demanou <demsking@gmail.com>
Requires-Python: >=3.12, <3.13
Project-URL: Documentation, https://demsking.gitlab.io/seto
Project-URL: Issues, https://gitlab.com/demsking/seto/-/issues
Project-URL: Say Thanks!, https://www.buymeacoffee.com/demsking
Project-URL: Source, https://gitlab.com/demsking/seto
